nifti2dicom/__init__.py
nifti2dicom/constants.py
nifti2dicom/converter.py
nifti2dicom/display.py
nifti2dicom/viewer.py
nifti2dicom-1.2.6.dist-info/LICENSE
nifti2dicom-1.2.6.dist-info/METADATA
nifti2dicom-1.2.6.dist-info/WHEEL
nifti2dicom-1.2.6.dist-info/entry_points.txt
nifti2dicom-1.2.6.dist-info/top_level.txt
nifti2dicom-1.2.6.dist-info/RECORD
