Metadata-Version: 2.1
Name: nifti2dicom
Version: 1.2.6
Summary: A package to convert NIfTI images to DICOM format using a reference DICOM series.
Author: Lalith Kumar Shiyam Sundar
License: MIT
Keywords: nifti dicom converter
License-File: LICENSE
Requires-Dist: nibabel
Requires-Dist: SimpleITK
Requires-Dist: emoji
Requires-Dist: rich
Requires-Dist: highdicom
Requires-Dist: pyfiglet
